fetch_embed/__init__.py
fetch_embed/embed_text.py
fetch_embed/fetch_embed.py
fetch_embed-0.1.6.dist-info/WHEEL
fetch_embed-0.1.6.dist-info/METADATA
fetch_embed-0.1.6.dist-info/RECORD
