Metadata-Version: 2.1
Name: fetch-embed
Version: 0.1.6
Summary: 
Home-page: https://github.com/ffreemt/fetch-embed
License: MIT
Author: freemt
Requires-Python: >=3.7,<4.0
Classifier: License :: OSI Approved :: MIT License
Classifier: Programming Language :: Python :: 3
Classifier: Programming Language :: Python :: 3.7
Classifier: Programming Language :: Python :: 3.8
Classifier: Programming Language :: Python :: 3.9
Requires-Dist: alive-progress (>=1.6.2,<2.0.0)
Requires-Dist: httpx (>=0.17.1,<0.18.0)
Requires-Dist: joblib (>=1.0.1,<2.0.0)
Requires-Dist: loguru (>=0.5.3,<0.6.0)
Requires-Dist: logzero (>=1.7.0,<2.0.0)
Requires-Dist: numpy (>=1.20.2,<2.0.0)
Requires-Dist: tqdm (>=4.60.0,<5.0.0)
Project-URL: Repository, https://github.com/ffreemt/fetch-embed
